amconll/__init__.py
amconll/amconll_tools.py
amconll-1.0.2.dist-info/METADATA
amconll-1.0.2.dist-info/WHEEL
amconll-1.0.2.dist-info/top_level.txt
amconll-1.0.2.dist-info/RECORD
